<annotation><folder>images</folder><filename>3425.jpg</filename><size><width>864</width><height>486</height><depth>3</depth></size><object><name>with_mask</name><bnbbox><xmin>123</xmin><ymin>246</ymin><xmax>269</xmax><ymax>369</ymax></bnbbox></object><object><name>with_mask</name><bnbbox><xmin>36</xmin><ymin>232</ymin><xmax>721</xmax><ymax>864</ymax></bnbbox></object><object><name>without_mask</name><bnbbox><xmin>176</xmin><ymin>243</ymin><xmax>579</xmax><ymax>631</ymax></bnbbox></object><object><name>without_mask</name><bnbbox><xmin>184</xmin><ymin>248</ymin><xmax>634</xmax><ymax>704</ymax></bnbbox></object></annotation>