<annotation><folder>images</folder><filename>1016.jpg</filename><size><width>2313</width><height>1494</height><depth>3</depth></size><object><name>with_mask</name><bnbbox><xmin>627</xmin><ymin>955</ymin><xmax>1330</xmax><ymax>1610</ymax></bnbbox></object><object><name>with_mask</name><bnbbox><xmin>649</xmin><ymin>928</ymin><xmax>886</xmax><ymax>1111</ymax></bnbbox></object><object><name>with_mask</name><bnbbox><xmin>442</xmin><ymin>716</ymin><xmax>484</xmax><ymax>864</ymax></bnbbox></object><object><name>with_mask</name><bnbbox><xmin>314</xmin><ymin>542</ymin><xmax>1601</xmax><ymax>1791</ymax></bnbbox></object><object><name>with_mask</name><bnbbox><xmin>268</xmin><ymin>591</ymin><xmax>727</xmax><ymax>997</ymax></bnbbox></object><object><name>with_mask</name><bnbbox><xmin>0</xmin><ymin>241</ymin><xmax>200</xmax><ymax>516</ymax></bnbbox></object><object><name>with_mask</name><bnbbox><xmin>196</xmin><ymin>432</ymin><xmax>1076</xmax><ymax>1246</ymax></bnbbox></object><object><name>with_mask</name><bnbbox><xmin>321</xmin><ymin>594</ymin><xmax>1918</xmax><ymax>2109</ymax></bnbbox></object><object><name>with_mask</name><bnbbox><xmin>376</xmin><ymin>605</ymin><xmax>1351</xmax><ymax>1542</ymax></bnbbox></object><object><name>with_mask</name><bnbbox><xmin>202</xmin><ymin>470</ymin><xmax>540</xmax><ymax>747</ymax></bnbbox></object><object><name>with_mask</name><bnbbox><xmin>296</xmin><ymin>542</ymin><xmax>346</xmax><ymax>641</ymax></bnbbox></object></annotation>