<annotation><folder>images</folder><filename>2064.png</filename><size><width>466</width><height>614</height><depth>3</depth></size><object><name>with_mask</name><bnbbox><xmin>101</xmin><ymin>181</ymin><xmax>365</xmax><ymax>403</ymax></bnbbox></object><object><name>mask_weared_incorrect</name><bnbbox><xmin>64</xmin><ymin>142</ymin><xmax>307</xmax><ymax>377</ymax></bnbbox></object><object><name>mask_weared_incorrect</name><bnbbox><xmin>114</xmin><ymin>164</ymin><xmax>122</xmax><ymax>187</ymax></bnbbox></object><object><name>without_mask</name><bnbbox><xmin>148</xmin><ymin>178</ymin><xmax>409</xmax><ymax>431</ymax></bnbbox></object></annotation>