<annotation><folder>images</folder><filename>2135.png</filename><size><width>958</width><height>582</height><depth>3</depth></size><object><name>with_mask</name><bnbbox><xmin>88</xmin><ymin>326</ymin><xmax>314</xmax><ymax>505</ymax></bnbbox></object><object><name>without_mask</name><bnbbox><xmin>69</xmin><ymin>288</ymin><xmax>80</xmax><ymax>337</ymax></bnbbox></object><object><name>with_mask</name><bnbbox><xmin>39</xmin><ymin>154</ymin><xmax>236</xmax><ymax>338</ymax></bnbbox></object><object><name>with_mask</name><bnbbox><xmin>196</xmin><ymin>313</ymin><xmax>472</xmax><ymax>529</ymax></bnbbox></object><object><name>without_mask</name><bnbbox><xmin>202</xmin><ymin>329</ymin><xmax>250</xmax><ymax>350</ymax></bnbbox></object><object><name>without_mask</name><bnbbox><xmin>67</xmin><ymin>575</ymin><xmax>583</xmax><ymax>945</ymax></bnbbox></object></annotation>