<annotation><folder>images</folder><filename>2661.png</filename><size><width>1031</width><height>631</height><depth>3</depth></size><object><name>with_mask</name><bnbbox><xmin>6</xmin><ymin>412</ymin><xmax>475</xmax><ymax>866</ymax></bnbbox></object><object><name>without_mask</name><bnbbox><xmin>79</xmin><ymin>208</ymin><xmax>189</xmax><ymax>323</ymax></bnbbox></object><object><name>without_mask</name><bnbbox><xmin>229</xmin><ymin>420</ymin><xmax>333</xmax><ymax>501</ymax></bnbbox></object></annotation>