<annotation><folder>images</folder><filename>2676.png</filename><size><width>982</width><height>587</height><depth>3</depth></size><object><name>with_mask</name><bnbbox><xmin>127</xmin><ymin>309</ymin><xmax>446</xmax><ymax>583</ymax></bnbbox></object><object><name>with_mask</name><bnbbox><xmin>117</xmin><ymin>363</ymin><xmax>749</xmax><ymax>942</ymax></bnbbox></object><object><name>with_mask</name><bnbbox><xmin>87</xmin><ymin>238</ymin><xmax>318</xmax><ymax>448</ymax></bnbbox></object></annotation>